setup.py
gaussian_binomial_96/Binomialdistribution.py
gaussian_binomial_96/Gaussiandistribution.py
gaussian_binomial_96/Generaldistribution.py
gaussian_binomial_96/__init__.py
gaussian_binomial_96.egg-info/PKG-INFO
gaussian_binomial_96.egg-info/SOURCES.txt
gaussian_binomial_96.egg-info/dependency_links.txt
gaussian_binomial_96.egg-info/not-zip-safe
gaussian_binomial_96.egg-info/top_level.txt