Metadata-Version: 1.0
Name: gaussian-binomial-96
Version: 1.0
Summary: Gaussian distributions
Home-page: UNKNOWN
Author: Paulo Akira
Author-email: pauloakira.simul@gmail.com
License: UNKNOWN
Platform: UNKNOWN
